[
   {
      "id":1,
      "type": "Category 1"
   },
   {
      "id":2,
      "type": "Category 2"
   },
   {
      "id":3,
      "type": "Category 3"
   },
   {
      "id":4,
      "type": "Category 4"
   },
   {
      "id":5,
      "type": "Category 5"
   },
   {
      "id":6,
      "type": "Category 6"
   },
   {
      "id":7,
      "type": "Category 7"
   },
   {
      "id":8,
      "type": "Category 8"
   },
   {
      "id":9,
      "type": "Category 9"
   },
   {
      "id":10,
      "type": "Category 10"
   },
   {
      "id":11,
      "type": "Category 11"
   },
   {
      "id":12,
      "type": "Category 12"
   },
   {
      "id":13,
      "type": "Category 13"
   }
]
